nexo/__init__.py
nexo/async_client.py
nexo/base_client.py
nexo/client.py
nexo/exceptions.py
nexo/helpers.py
nexo/response_serializers.py
python_nexo-1.0.3.dist-info/LICENSE
python_nexo-1.0.3.dist-info/METADATA
python_nexo-1.0.3.dist-info/WHEEL
python_nexo-1.0.3.dist-info/top_level.txt
python_nexo-1.0.3.dist-info/RECORD
