Metadata-Version: 2.1
Name: python-nexo
Version: 1.0.3
Summary: Nexo Pro REST API python implementation
Home-page: https://github.com/guilyx/python-nexo
Author: Erwin Lejeune
Author-email: erwin.lejeune15@gmail.com
License: MIT
Keywords: nexo crypto exchange rest api bitcoin ethereum btc eth neo
Classifier: Intended Audience :: Developers
Classifier: License :: OSI Approved :: MIT License
Classifier: Operating System :: OS Independent
Classifier: Programming Language :: Python :: 3
Classifier: Programming Language :: Python :: 3.5
Classifier: Programming Language :: Python :: 3.6
Classifier: Programming Language :: Python :: 3.7
Classifier: Programming Language :: Python
Classifier: Topic :: Software Development :: Libraries :: Python Modules
License-File: LICENSE
Requires-Dist: aiohttp (==3.8.3)
Requires-Dist: requests (==2.28.1)
